{
  "generator-jhipster": {
    "promptValues": {
      "packageName": "frauca",
      "nativeLanguage": "en"
    },
    "jhipsterVersion": "4.8.2",
    "baseName": "helloFrauca",
    "packageName": "frauca",
    "packageFolder": "frauca",
    "serverPort": "8080",
    "authenticationType": "jwt",
    "hibernateCache": "ehcache",
    "clusteredHttpSession": false,
    "websocket": false,
    "databaseType": "sql",
    "devDatabaseType": "h2Disk",
    "prodDatabaseType": "mysql",
    "searchEngine": false,
    "messageBroker": false,
    "serviceDiscoveryType": false,
    "buildTool": "maven",
    "enableSocialSignIn": false,
    "enableSwaggerCodegen": false,
    "jwtSecretKey": "cadb233169c3fd54b0b0fb125166a77dacef5d0c",
    "clientFramework": "angularX",
    "useSass": false,
    "clientPackageManager": "yarn",
    "applicationType": "monolith",
    "testFrameworks": [],
    "jhiPrefix": "jhi",
    "enableTranslation": true,
    "nativeLanguage": "en",
    "languages": [
      "en",
      "ca",
      "fr",
      "es"
    ]
  }
}